skillreadiness/__init__.py
skillreadiness/__main__.py
skillreadiness/cli.py
skillreadiness/core/__init__.py
skillreadiness/core/loader.py
skillreadiness/core/models.py
skillreadiness/core/orchestrator.py
skillreadiness/core/taxonomy.py
skillreadiness/providers/__init__.py
skillreadiness/providers/base.py
skillreadiness/providers/heuristic_provider.py
skillreadiness/reports/__init__.py
skillreadiness/reports/json_report.py
skillreadiness/reports/markdown_report.py
skillreadiness/reports/sarif.py
skill_readiness_analyzer-0.1.0.dist-info/METADATA
skill_readiness_analyzer-0.1.0.dist-info/WHEEL
skill_readiness_analyzer-0.1.0.dist-info/entry_points.txt
skill_readiness_analyzer-0.1.0.dist-info/licenses/LICENSE
skill_readiness_analyzer-0.1.0.dist-info/RECORD
