Metadata-Version: 2.4
Name: skill-readiness-analyzer
Version: 0.1.0
Summary: Production readiness scanner for AI Agent Skills - quality gates, best practices, and operational excellence
Project-URL: Homepage, https://github.com/nik-kale/skill-readiness-analyzer
Project-URL: Documentation, https://github.com/nik-kale/skill-readiness-analyzer#readme
Project-URL: Repository, https://github.com/nik-kale/skill-readiness-analyzer
Project-URL: Issues, https://github.com/nik-kale/skill-readiness-analyzer/issues
Author: Nik Kale
License-Expression: MIT
License-File: LICENSE
Keywords: agent-skills,ai,best-practices,claude,codex,cursor,quality,readiness,scanner
Classifier: Development Status :: 4 - Beta
Classifier: Environment :: Console
Classifier: Intended Audience :: Developers
Classifier: License :: OSI Approved :: MIT License
Classifier: Operating System :: OS Independent
Classifier: Programming Language :: Python :: 3
Classifier: Programming Language :: Python :: 3.10
Classifier: Programming Language :: Python :: 3.11
Classifier: Programming Language :: Python :: 3.12
Classifier: Topic :: Software Development :: Quality Assurance
Classifier: Topic :: Software Development :: Testing
Requires-Python: >=3.10
Requires-Dist: click>=8.1.0
Requires-Dist: pydantic>=2.0.0
Requires-Dist: python-frontmatter>=1.0.0
Requires-Dist: rich>=13.0.0
Requires-Dist: tiktoken>=0.5.0
Provides-Extra: all
Requires-Dist: litellm>=1.0.0; extra == 'all'
Requires-Dist: mypy>=1.0.0; extra == 'all'
Requires-Dist: pytest-asyncio>=0.21.0; extra == 'all'
Requires-Dist: pytest-cov>=4.0.0; extra == 'all'
Requires-Dist: pytest>=7.0.0; extra == 'all'
Requires-Dist: ruff>=0.1.0; extra == 'all'
Requires-Dist: yara-python>=4.3.0; extra == 'all'
Provides-Extra: dev
Requires-Dist: mypy>=1.0.0; extra == 'dev'
Requires-Dist: pytest-asyncio>=0.21.0; extra == 'dev'
Requires-Dist: pytest-cov>=4.0.0; extra == 'dev'
Requires-Dist: pytest>=7.0.0; extra == 'dev'
Requires-Dist: ruff>=0.1.0; extra == 'dev'
Provides-Extra: llm
Requires-Dist: litellm>=1.0.0; extra == 'llm'
Provides-Extra: yara
Requires-Dist: yara-python>=4.3.0; extra == 'yara'
